{"v":"5.5.7","meta":{"g":"LottieFiles AE 0.1.20","a":"Sadjad","k":"code icon","d":"code icon for you designed, enjoy","tc":"none"},"fr":30,"ip":0,"op":43,"w":250,"h":250,"nm":"code_lottie","ddd":0,"assets":[],"layers":[{"ddd":0,"ind":1,"ty":3,"nm":"Null 2","sr":1,"ks":{"o":{"a":0,"k":0,"ix":11},"r":{"a":0,"k":0,"ix":10},"p":{"a":1,"k":[{"i":{"x":0.21,"y":1},"o":{"x":0.79,"y":0},"t":5,"s":[125,125,0],"to":[-1.333,0,0],"ti":[1.333,0,0]},{"i":{"x":0.21,"y":0.21},"o":{"x":0.79,"y":0.79},"t":18,"s":[117,125,0],"to":[0,0,0],"ti":[0,0,0]},{"i":{"x":0.21,"y":1},"o":{"x":0.79,"y":0},"t":23,"s":[117,125,0],"to":[1.333,0,0],"ti":[-1.333,0,0]},{"t":37,"s":[125,125,0]}],"ix":2},"a":{"a":0,"k":[0,0,0],"ix":1},"s":{"a":1,"k":[{"i":{"x":[0.21,0.21,0.21],"y":[1,1,1]},"o":{"x":[0.79,0.79,0.79],"y":[0,0,0]},"t":5,"s":[100,100,100]},{"i":{"x":[0.21,0.21,0.21],"y":[1,1,1]},"o":{"x":[0.79,0.79,0.79],"y":[0,0,0]},"t":18,"s":[70,70,100]},{"i":{"x":[0.21,0.21,0.21],"y":[1,1,1]},"o":{"x":[0.79,0.79,0.79],"y":[0,0,0]},"t":23,"s":[70,70,100]},{"t":37,"s":[100,100,100]}],"ix":6}},"ao":0,"ip":0,"op":241,"st":0,"bm":0},{"ddd":0,"ind":2,"ty":4,"nm":"code Outlines","parent":1,"sr":1,"ks":{"o":{"a":0,"k":100,"ix":11},"r":{"a":0,"k":0,"ix":10},"p":{"a":0,"k":[23,-0.5,0],"ix":2},"a":{"a":0,"k":[-0.03,-29.53,0],"ix":1},"s":{"a":0,"k":[100,100,100],"ix":6}},"ao":0,"shapes":[{"ty":"gr","it":[{"ind":0,"ty":"sh","ix":1,"ks":{"a":0,"k":{"i":[[0,0],[11.248,0],[0,-13.862],[-12.493,0],[-0.955,9.297],[0,0],[5.52,0],[0,9.587],[-6.931,0],[-0.913,-4.648]],"o":[[-0.789,-8.591],[-12.41,0],[0,14.111],[10.5,0],[0,0],[-1.038,5.063],[-6.973,0],[0,-9.38],[5.852,0],[0,0]],"v":[[-49.876,-28.638],[-68.761,-44.451],[-89.305,-21.831],[-68.678,0.83],[-49.793,-14.775],[-58.426,-14.775],[-68.595,-6.682],[-80.174,-21.831],[-68.678,-36.98],[-58.426,-28.638]],"c":true},"ix":2},"nm":"c","mn":"ADBE Vector Shape - Group","hd":false},{"ty":"fl","c":{"a":0,"k":[0,0,0,1],"ix":4},"o":{"a":0,"k":100,"ix":5},"r":1,"bm":0,"nm":"Fill 1","mn":"ADBE Vector Graphic - Fill","hd":false},{"ty":"tr","p":{"a":0,"k":[0,0],"ix":2},"a":{"a":0,"k":[0,0],"ix":1},"s":{"a":0,"k":[100,100],"ix":3},"r":{"a":0,"k":0,"ix":6},"o":{"a":1,"k":[{"i":{"x":[0.21],"y":[1]},"o":{"x":[0.79],"y":[0]},"t":13,"s":[0]},{"i":{"x":[0.21],"y":[1]},"o":{"x":[0.79],"y":[0]},"t":14,"s":[100]},{"i":{"x":[0.21],"y":[1]},"o":{"x":[0.79],"y":[0]},"t":27,"s":[100]},{"t":28,"s":[0]}],"ix":7},"sk":{"a":0,"k":0,"ix":4},"sa":{"a":0,"k":0,"ix":5},"nm":"Transform"}],"nm":"c","np":3,"cix":2,"bm":0,"ix":1,"mn":"ADBE Vector Group","hd":false},{"ty":"gr","it":[{"ind":0,"ty":"sh","ix":1,"ks":{"a":0,"k":{"i":[[-12.493,0],[0,14.07],[12.451,0],[0,-14.028]],"o":[[12.493,0],[0,-14.028],[-12.451,0],[0,14.07]],"v":[[-24.684,0.83],[-3.973,-21.831],[-24.684,-44.451],[-45.394,-21.831]],"c":true},"ix":2},"nm":"o","mn":"ADBE Vector Shape - Group","hd":false},{"ind":1,"ty":"sh","ix":2,"ks":{"a":0,"k":{"i":[[7.056,0],[0,9.712],[-7.014,0],[0,-9.67]],"o":[[-7.014,0],[0,-9.67],[7.014,0],[0,9.712]],"v":[[-24.684,-6.558],[-36.263,-21.831],[-24.684,-37.063],[-13.104,-21.831]],"c":true},"ix":2},"nm":"o","mn":"ADBE Vector Shape - Group","hd":false},{"ty":"mm","mm":1,"nm":"Merge Paths 1","mn":"ADBE Vector Filter - Merge","hd":false},{"ty":"fl","c":{"a":0,"k":[0,0,0,1],"ix":4},"o":{"a":0,"k":100,"ix":5},"r":1,"bm":0,"nm":"Fill 1","mn":"ADBE Vector Graphic - Fill","hd":false},{"ty":"tr","p":{"a":0,"k":[0,0],"ix":2},"a":{"a":0,"k":[0,0],"ix":1},"s":{"a":0,"k":[100,100],"ix":3},"r":{"a":0,"k":0,"ix":6},"o":{"a":1,"k":[{"i":{"x":[0.21],"y":[1]},"o":{"x":[0.79],"y":[0]},"t":14,"s":[0]},{"i":{"x":[0.21],"y":[1]},"o":{"x":[0.79],"y":[0]},"t":15,"s":[100]},{"i":{"x":[0.21],"y":[1]},"o":{"x":[0.79],"y":[0]},"t":26,"s":[100]},{"t":27,"s":[0]}],"ix":7},"sk":{"a":0,"k":0,"ix":4},"sa":{"a":0,"k":0,"ix":5},"nm":"Transform"}],"nm":"o","np":5,"cix":2,"bm":0,"ix":2,"mn":"ADBE Vector Group","hd":false},{"ty":"gr","it":[{"ind":0,"ty":"sh","ix":1,"ks":{"a":0,"k":{"i":[[-11.04,0],[-2.573,4.98],[0,0],[0,0],[0,0],[0,0],[0,0],[0,0],[0,0],[6.267,0],[0,-13.779]],"o":[[6.35,0],[0,0],[0,0],[0,0],[0,0],[0,0],[0,0],[0,0],[-2.449,-4.814],[-10.957,0],[0,13.779]],"v":[[19.352,0.747],[33.256,-7.429],[33.422,-7.429],[33.422,0],[42.138,0],[42.138,-59.89],[33.131,-59.89],[33.131,-36.399],[32.965,-36.399],[19.269,-44.368],[1.007,-21.831]],"c":true},"ix":2},"nm":"d","mn":"ADBE Vector Shape - Group","hd":false},{"ind":1,"ty":"sh","ix":2,"ks":{"a":0,"k":{"i":[[-7.097,0],[0,-9.048],[6.89,0],[0,9.214]],"o":[[6.89,0],[0,9.131],[-7.097,0],[0,-9.172]],"v":[[21.718,-36.814],[33.214,-21.831],[21.718,-6.848],[10.18,-21.831]],"c":true},"ix":2},"nm":"d","mn":"ADBE Vector Shape - Group","hd":false},{"ty":"mm","mm":1,"nm":"Merge Paths 1","mn":"ADBE Vector Filter - Merge","hd":false},{"ty":"fl","c":{"a":0,"k":[0,0,0,1],"ix":4},"o":{"a":0,"k":100,"ix":5},"r":1,"bm":0,"nm":"Fill 1","mn":"ADBE Vector Graphic - Fill","hd":false},{"ty":"tr","p":{"a":0,"k":[0,0],"ix":2},"a":{"a":0,"k":[0,0],"ix":1},"s":{"a":0,"k":[100,100],"ix":3},"r":{"a":0,"k":0,"ix":6},"o":{"a":1,"k":[{"i":{"x":[0.21],"y":[1]},"o":{"x":[0.79],"y":[0]},"t":15,"s":[0]},{"i":{"x":[0.21],"y":[1]},"o":{"x":[0.79],"y":[0]},"t":16,"s":[100]},{"i":{"x":[0.21],"y":[1]},"o":{"x":[0.79],"y":[0]},"t":25,"s":[100]},{"t":26,"s":[0]}],"ix":7},"sk":{"a":0,"k":0,"ix":4},"sa":{"a":0,"k":0,"ix":5},"nm":"Transform"}],"nm":"d","np":5,"cix":2,"bm":0,"ix":3,"mn":"ADBE Vector Group","hd":false},{"ty":"gr","it":[{"ind":0,"ty":"sh","ix":1,"ks":{"a":0,"k":{"i":[[-6.267,0],[-0.208,-6.682],[0,0]],"o":[[6.267,0],[0,0],[0.457,-6.599]],"v":[[69.572,-37.229],[80.28,-25.857],[58.449,-25.857]],"c":true},"ix":2},"nm":"e","mn":"ADBE Vector Shape - Group","hd":false},{"ind":1,"ty":"sh","ix":2,"ks":{"a":0,"k":{"i":[[0,0],[5.105,0],[0,7.595],[0,0],[0,0],[0,0],[12.119,0],[0,-13.696],[-12.825,0],[-1.245,7.969]],"o":[[-1.204,3.818],[-7.18,0],[0,0],[0,0],[0,0],[0,-13.24],[-12.327,0],[0,13.779],[10.002,0],[0,0]],"v":[[80.238,-12.825],[70.153,-6.433],[58.407,-19.05],[58.407,-19.59],[89.245,-19.59],[89.245,-22.661],[69.572,-44.451],[49.359,-21.624],[69.945,0.83],[88.747,-12.825]],"c":true},"ix":2},"nm":"e","mn":"ADBE Vector Shape - Group","hd":false},{"ty":"mm","mm":1,"nm":"Merge Paths 1","mn":"ADBE Vector Filter - Merge","hd":false},{"ty":"fl","c":{"a":0,"k":[0,0,0,1],"ix":4},"o":{"a":0,"k":100,"ix":5},"r":1,"bm":0,"nm":"Fill 1","mn":"ADBE Vector Graphic - Fill","hd":false},{"ty":"tr","p":{"a":0,"k":[0,0],"ix":2},"a":{"a":0,"k":[0,0],"ix":1},"s":{"a":0,"k":[100,100],"ix":3},"r":{"a":0,"k":0,"ix":6},"o":{"a":1,"k":[{"i":{"x":[0.21],"y":[1]},"o":{"x":[0.79],"y":[0]},"t":16,"s":[0]},{"i":{"x":[0.21],"y":[1]},"o":{"x":[0.79],"y":[0]},"t":17,"s":[100]},{"i":{"x":[0.21],"y":[1]},"o":{"x":[0.79],"y":[0]},"t":24,"s":[100]},{"t":25,"s":[0]}],"ix":7},"sk":{"a":0,"k":0,"ix":4},"sa":{"a":0,"k":0,"ix":5},"nm":"Transform"}],"nm":"e","np":5,"cix":2,"bm":0,"ix":4,"mn":"ADBE Vector Group","hd":false}],"ip":5,"op":246,"st":5,"bm":0},{"ddd":0,"ind":3,"ty":4,"nm":"dash","parent":1,"sr":1,"ks":{"o":{"a":0,"k":100,"ix":11},"r":{"a":0,"k":0,"ix":10},"p":{"a":1,"k":[{"i":{"x":0.21,"y":1},"o":{"x":0.79,"y":0},"t":5,"s":[-0.162,2.5,0],"to":[-13.333,0,0],"ti":[13.333,0,0]},{"i":{"x":0.21,"y":0.21},"o":{"x":0.79,"y":0.79},"t":18,"s":[-80.162,2.5,0],"to":[0,0,0],"ti":[0,0,0]},{"i":{"x":0.21,"y":1},"o":{"x":0.79,"y":0},"t":23,"s":[-80.162,2.5,0],"to":[13.333,0,0],"ti":[-13.333,0,0]},{"t":37,"s":[-0.162,2.5,0]}],"ix":2},"a":{"a":0,"k":[-0.75,1.5,0],"ix":1},"s":{"a":0,"k":[100,100,100],"ix":6}},"ao":0,"shapes":[{"ty":"gr","it":[{"ind":0,"ty":"sh","ix":1,"ks":{"a":1,"k":[{"i":{"x":0.21,"y":1},"o":{"x":0.79,"y":0},"t":5,"s":[{"i":[[0,0],[0,0]],"o":[[0,0],[0,0]],"v":[[-23.5,65],[22,-62]],"c":false}]},{"i":{"x":0.21,"y":1},"o":{"x":0.79,"y":0},"t":18,"s":[{"i":[[0,0],[0,0]],"o":[[0,0],[0,0]],"v":[[-14,37],[14,-39]],"c":false}]},{"i":{"x":0.21,"y":1},"o":{"x":0.79,"y":0},"t":23,"s":[{"i":[[0,0],[0,0]],"o":[[0,0],[0,0]],"v":[[-14,37],[14,-39]],"c":false}]},{"t":37,"s":[{"i":[[0,0],[0,0]],"o":[[0,0],[0,0]],"v":[[-23.5,65],[22,-62]],"c":false}]}],"ix":2},"nm":"Path 1","mn":"ADBE Vector Shape - Group","hd":false},{"ty":"st","c":{"a":0,"k":[0,0,0,1],"ix":3},"o":{"a":0,"k":100,"ix":4},"w":{"a":0,"k":13,"ix":5},"lc":2,"lj":1,"ml":4,"bm":0,"nm":"Stroke 1","mn":"ADBE Vector Graphic - Stroke","hd":false},{"ty":"tr","p":{"a":0,"k":[0,0],"ix":2},"a":{"a":0,"k":[0,0],"ix":1},"s":{"a":0,"k":[100,100],"ix":3},"r":{"a":0,"k":0,"ix":6},"o":{"a":0,"k":100,"ix":7},"sk":{"a":0,"k":0,"ix":4},"sa":{"a":0,"k":0,"ix":5},"nm":"Transform"}],"nm":"Shape 1","np":3,"cix":2,"bm":0,"ix":1,"mn":"ADBE Vector Group","hd":false},{"ty":"tm","s":{"a":0,"k":100,"ix":1},"e":{"a":1,"k":[{"i":{"x":[0.21],"y":[1]},"o":{"x":[0.79],"y":[0]},"t":11,"s":[100]},{"i":{"x":[0.21],"y":[1]},"o":{"x":[0.79],"y":[0]},"t":18,"s":[0]},{"i":{"x":[0.21],"y":[1]},"o":{"x":[0.79],"y":[0]},"t":23,"s":[0]},{"t":30,"s":[100]}],"ix":2},"o":{"a":0,"k":0,"ix":3},"m":1,"ix":2,"nm":"Trim Paths 1","mn":"ADBE Vector Filter - Trim","hd":false}],"ip":0,"op":241,"st":0,"bm":0},{"ddd":0,"ind":4,"ty":4,"nm":"<","parent":1,"sr":1,"ks":{"o":{"a":0,"k":100,"ix":11},"r":{"a":0,"k":0,"ix":10},"p":{"a":1,"k":[{"i":{"x":0.21,"y":1},"o":{"x":0.79,"y":0},"t":5,"s":[-58.333,0,0],"to":[-9.971,-0.167,0],"ti":[9.971,0.167,0]},{"i":{"x":0.21,"y":0.21},"o":{"x":0.79,"y":0.79},"t":18,"s":[-118.157,-1,0],"to":[0,0,0],"ti":[0,0,0]},{"i":{"x":0.21,"y":1},"o":{"x":0.79,"y":0},"t":23,"s":[-118.157,-1,0],"to":[9.971,0.167,0],"ti":[-9.971,-0.167,0]},{"t":37,"s":[-58.333,0,0]}],"ix":2},"a":{"a":0,"k":[38,63,0],"ix":1},"s":{"a":0,"k":[100,100,100],"ix":6}},"ao":0,"shapes":[{"ty":"gr","it":[{"ind":0,"ty":"sh","ix":1,"ks":{"a":1,"k":[{"i":{"x":0.21,"y":1},"o":{"x":0.79,"y":0},"t":5,"s":[{"i":[[0,0],[0,0],[0,0]],"o":[[0,0],[0,0],[0,0]],"v":[[25,-50],[-25,0],[25,50]],"c":false}]},{"i":{"x":0.21,"y":1},"o":{"x":0.79,"y":0},"t":18,"s":[{"i":[[0,0],[0,0],[0,0]],"o":[[0,0],[0,0],[0,0]],"v":[[5.171,-30.329],[-25,0],[6.671,31.829]],"c":false}]},{"i":{"x":0.21,"y":1},"o":{"x":0.79,"y":0},"t":23,"s":[{"i":[[0,0],[0,0],[0,0]],"o":[[0,0],[0,0],[0,0]],"v":[[5.171,-30.329],[-25,0],[6.671,31.829]],"c":false}]},{"t":37,"s":[{"i":[[0,0],[0,0],[0,0]],"o":[[0,0],[0,0],[0,0]],"v":[[25,-50],[-25,0],[25,50]],"c":false}]}],"ix":2},"nm":"Path 1","mn":"ADBE Vector Shape - Group","hd":false},{"ty":"st","c":{"a":0,"k":[0,0,0,1],"ix":3},"o":{"a":0,"k":100,"ix":4},"w":{"a":0,"k":13,"ix":5},"lc":2,"lj":2,"bm":0,"nm":"Stroke 1","mn":"ADBE Vector Graphic - Stroke","hd":false},{"ty":"tr","p":{"a":0,"k":[38,63],"ix":2},"a":{"a":0,"k":[0,0],"ix":1},"s":{"a":0,"k":[100,100],"ix":3},"r":{"a":0,"k":0,"ix":6},"o":{"a":0,"k":100,"ix":7},"sk":{"a":0,"k":0,"ix":4},"sa":{"a":0,"k":0,"ix":5},"nm":"Transform"}],"nm":"Group 1","np":2,"cix":2,"bm":0,"ix":1,"mn":"ADBE Vector Group","hd":false}],"ip":0,"op":241,"st":0,"bm":0},{"ddd":0,"ind":5,"ty":4,"nm":">","parent":1,"sr":1,"ks":{"o":{"a":0,"k":100,"ix":11},"r":{"a":0,"k":0,"ix":10},"p":{"a":1,"k":[{"i":{"x":0.21,"y":1},"o":{"x":0.79,"y":0},"t":5,"s":[58.333,0,0],"to":[22.431,0,0],"ti":[-22.431,0,0]},{"i":{"x":0.21,"y":0.21},"o":{"x":0.79,"y":0.79},"t":18,"s":[192.921,0,0],"to":[0,0,0],"ti":[0,0,0]},{"i":{"x":0.21,"y":1},"o":{"x":0.79,"y":0},"t":23,"s":[192.921,0,0],"to":[-22.431,0,0],"ti":[22.431,0,0]},{"t":37,"s":[58.333,0,0]}],"ix":2},"a":{"a":0,"k":[38,63,0],"ix":1},"s":{"a":0,"k":[100,100,100],"ix":6}},"ao":0,"shapes":[{"ty":"gr","it":[{"ind":0,"ty":"sh","ix":1,"ks":{"a":1,"k":[{"i":{"x":0.21,"y":1},"o":{"x":0.79,"y":0},"t":5,"s":[{"i":[[0,0],[0,0],[0,0]],"o":[[0,0],[0,0],[0,0]],"v":[[-25,50],[25,0],[-25,-50]],"c":false}]},{"i":{"x":0.21,"y":1},"o":{"x":0.79,"y":0},"t":18,"s":[{"i":[[0,0],[0,0],[0,0]],"o":[[0,0],[0,0],[0,0]],"v":[[-62.868,32.632],[-30.5,0],[-62.618,-31.882]],"c":false}]},{"i":{"x":0.21,"y":1},"o":{"x":0.79,"y":0},"t":23,"s":[{"i":[[0,0],[0,0],[0,0]],"o":[[0,0],[0,0],[0,0]],"v":[[-62.868,32.632],[-30.5,0],[-62.618,-31.882]],"c":false}]},{"t":37,"s":[{"i":[[0,0],[0,0],[0,0]],"o":[[0,0],[0,0],[0,0]],"v":[[-25,50],[25,0],[-25,-50]],"c":false}]}],"ix":2},"nm":"Path 1","mn":"ADBE Vector Shape - Group","hd":false},{"ty":"st","c":{"a":0,"k":[0,0,0,1],"ix":3},"o":{"a":0,"k":100,"ix":4},"w":{"a":0,"k":13,"ix":5},"lc":2,"lj":2,"bm":0,"nm":"Stroke 1","mn":"ADBE Vector Graphic - Stroke","hd":false},{"ty":"tr","p":{"a":0,"k":[38,63],"ix":2},"a":{"a":0,"k":[0,0],"ix":1},"s":{"a":0,"k":[100,100],"ix":3},"r":{"a":0,"k":0,"ix":6},"o":{"a":0,"k":100,"ix":7},"sk":{"a":0,"k":0,"ix":4},"sa":{"a":0,"k":0,"ix":5},"nm":"Transform"}],"nm":"Group 1","np":2,"cix":2,"bm":0,"ix":1,"mn":"ADBE Vector Group","hd":false}],"ip":0,"op":241,"st":0,"bm":0}],"markers":[]}